<servers><win64 url="https://downloads.lms-community.org/LyrionMusicServer_v9.1.1/LyrionMusicServer-9.1.1-win64.exe" version="9.1.1" revision="1779815526" size="14 MB" md5="80dc96b11ea6ae2df75df67ef9bae00e"/><macos url="https://downloads.lms-community.org/LyrionMusicServer_v9.1.1/LyrionMusicServer-9.1.1.dmg" version="9.1.1" revision="1779815526" size="43 MB" md5="879ae0a31834f07a96e31ac8d323e850"/><rpm url="https://downloads.lms-community.org/LyrionMusicServer_v9.1.1/lyrionmusicserver-9.1.1-1.noarch.rpm" version="9.1.1" revision="1779815526" size="81 MB" md5="a51f590012a55205e1137cc3d4390059"/><encore url="https://downloads.lms-community.org/LyrionMusicServer_v9.1.1/lyrionmusicserver-9.1.1-MusicalFidelity.tgz" version="9.1.1" revision="1779815526" size="17 MB" md5="521bbb9223454ba58b35a88d295f64c4"/><tararm url="https://downloads.lms-community.org/LyrionMusicServer_v9.1.1/lyrionmusicserver-9.1.1-arm-linux.tgz" version="9.1.1" revision="1779815526" size="59 MB" md5="f8553218f3a2bbbf6ffb5e203f818f3b"/><nocpan url="https://downloads.lms-community.org/LyrionMusicServer_v9.1.1/lyrionmusicserver-9.1.1-noCPAN.tgz" version="9.1.1" revision="1779815526" size="14 MB" md5="9582ff1e409c82733cc9e6bca59d9511"/><pcp url="https://downloads.lms-community.org/LyrionMusicServer_v9.1.1/lyrionmusicserver-9.1.1.tcz" version="9.1.1" revision="1779815526" size="15 MB" md5="1de0859da63260f45a61bc620473527b"/><src url="https://downloads.lms-community.org/LyrionMusicServer_v9.1.1/lyrionmusicserver-9.1.1.tgz" version="9.1.1" revision="1779815526" size="118 MB" md5="11a05b8a79515fb4dfb303c5e0abc6e1"/><deb url="https://downloads.lms-community.org/LyrionMusicServer_v9.1.1/lyrionmusicserver_9.1.1_all.deb" version="9.1.1" revision="1779815526" size="61 MB" md5="eef92394c91b1c0ed957fa18f3d0ae86"/><debamd64 url="https://downloads.lms-community.org/LyrionMusicServer_v9.1.1/lyrionmusicserver_9.1.1_amd64.deb" version="9.1.1" revision="1779815526" size="20 MB" md5="ed0d8380bd893236d78add5e3144122d"/><debarm url="https://downloads.lms-community.org/LyrionMusicServer_v9.1.1/lyrionmusicserver_9.1.1_arm.deb" version="9.1.1" revision="1779815526" size="26 MB" md5="a9955f0914faee9a7045a2ca7b1fa1d5"/><osx url="https://downloads.lms-community.org/LyrionMusicServer_v9.1.1/LyrionMusicServer-9.1.1.dmg" version="9.1.1" revision="1779815526" size="43 MB" md5="879ae0a31834f07a96e31ac8d323e850"/></servers>