{"latest":{"win64":{"url":"https://downloads.lms-community.org/LyrionMusicServer_v9.1.0/LyrionMusicServer-9.1.0-win64.exe","version":"9.1.0","revision":"1759466965","size":"14 MB","md5":"75c285f2b8b8cde1745590beef459e5d"},"macos":{"url":"https://downloads.lms-community.org/LyrionMusicServer_v9.1.0/LyrionMusicServer-9.1.0.dmg","version":"9.1.0","revision":"1759466965","size":"43 MB","md5":"5f735a9bc5ef93b3e1fd61b3470f419b"},"rpm":{"url":"https://downloads.lms-community.org/LyrionMusicServer_v9.1.0/lyrionmusicserver-9.1.0-1.noarch.rpm","version":"9.1.0","revision":"1759466965","size":"81 MB","md5":"2cdc56b63cfbee784a51fc081bab0373"},"encore":{"url":"https://downloads.lms-community.org/LyrionMusicServer_v9.1.0/lyrionmusicserver-9.1.0-MusicalFidelity.tgz","version":"9.1.0","revision":"1759466965","size":"17 MB","md5":"499ba274349b9bcede4e5adc30bdbb43"},"tararm":{"url":"https://downloads.lms-community.org/LyrionMusicServer_v9.1.0/lyrionmusicserver-9.1.0-arm-linux.tgz","version":"9.1.0","revision":"1759466965","size":"59 MB","md5":"8a4c6fbdb6a9e7a46cb3ad5d8f75c34e"},"nocpan":{"url":"https://downloads.lms-community.org/LyrionMusicServer_v9.1.0/lyrionmusicserver-9.1.0-noCPAN.tgz","version":"9.1.0","revision":"1759466965","size":"14 MB","md5":"a1bc744bb451ff8e6cdc3f70a008f67f"},"pcp":{"url":"https://downloads.lms-community.org/LyrionMusicServer_v9.1.0/lyrionmusicserver-9.1.0.tcz","version":"9.1.0","revision":"1759466965","size":"15 MB","md5":"22344b0154752f7e3d8cd85e1c336039"},"src":{"url":"https://downloads.lms-community.org/LyrionMusicServer_v9.1.0/lyrionmusicserver-9.1.0.tgz","version":"9.1.0","revision":"1759466965","size":"118 MB","md5":"514a55d6ab736ba771542855889c7cc8"},"deb":{"url":"https://downloads.lms-community.org/LyrionMusicServer_v9.1.0/lyrionmusicserver_9.1.0_all.deb","version":"9.1.0","revision":"1759466965","size":"61 MB","md5":"744cb2339aebc1b1bd59a4521ee8a1b1"},"debamd64":{"url":"https://downloads.lms-community.org/LyrionMusicServer_v9.1.0/lyrionmusicserver_9.1.0_amd64.deb","version":"9.1.0","revision":"1759466965","size":"20 MB","md5":"eb4f9ac52218cc17af6f92722b56eb4c"},"debarm":{"url":"https://downloads.lms-community.org/LyrionMusicServer_v9.1.0/lyrionmusicserver_9.1.0_arm.deb","version":"9.1.0","revision":"1759466965","size":"26 MB","md5":"65aeaae0dd4f7fdb95617339c2846d6f"},"osx":{"url":"https://downloads.lms-community.org/LyrionMusicServer_v9.1.0/LyrionMusicServer-9.1.0.dmg","version":"9.1.0","revision":"1759466965","size":"43 MB","md5":"5f735a9bc5ef93b3e1fd61b3470f419b"}},"9.2.0":{"win64":{"url":"https://downloads.lms-community.org/nightly/LyrionMusicServer-9.1.0-1771315634-win64.exe","version":"9.1.0","revision":"1771315634","size":"14 MB","md5":"6883f511c87ebf0e4beab1c9478085f7"},"macos":{"url":"https://downloads.lms-community.org/nightly/LyrionMusicServer-9.1.0-1771315634.dmg","version":"9.1.0","revision":"1771315634","size":"43 MB","md5":"3a79ee0d3c8d9878674f8c67d28c918d"},"rpm":{"url":"https://downloads.lms-community.org/nightly/lyrionmusicserver-9.1.0-0.1.1771315634.noarch.rpm","version":"9.1.0","revision":"1771315634","size":"81 MB","md5":"1931a9ce92806268a0f1e90e9d6d2882"},"encore":{"url":"https://downloads.lms-community.org/nightly/lyrionmusicserver-9.1.0-1771315634-MusicalFidelity.tgz","version":"9.1.0","revision":"1771315634","size":"17 MB","md5":"1fd0ba920c4f650616eca56670a87389"},"tararm":{"url":"https://downloads.lms-community.org/nightly/lyrionmusicserver-9.1.0-1771315634-arm-linux.tgz","version":"9.1.0","revision":"1771315634","size":"59 MB","md5":"2bd9db9abff45b1bbcefe40e823aeb95"},"nocpan":{"url":"https://downloads.lms-community.org/nightly/lyrionmusicserver-9.1.0-1771315634-noCPAN.tgz","version":"9.1.0","revision":"1771315634","size":"14 MB","md5":"c8941246bdb65c3d8679e0859f775e47"},"pcp":{"url":"https://downloads.lms-community.org/nightly/lyrionmusicserver-9.1.0-1771315634.tcz","version":"9.1.0","revision":"1771315634","size":"15 MB","md5":"74fe0e5af3ec6fe009cbe13086c8bdb7"},"src":{"url":"https://downloads.lms-community.org/nightly/lyrionmusicserver-9.1.0-1771315634.tgz","version":"9.1.0","revision":"1771315634","size":"118 MB","md5":"448583a306ad5dfc5c1f1a31afc14d2f"},"deb":{"url":"https://downloads.lms-community.org/nightly/lyrionmusicserver_9.1.0~1771315634_all.deb","version":"9.1.0","revision":"1771315634","size":"60 MB","md5":"ea9bf9e08df8651af8595fdd14e48dff"},"debamd64":{"url":"https://downloads.lms-community.org/nightly/lyrionmusicserver_9.1.0~1771315634_amd64.deb","version":"9.1.0","revision":"1771315634","size":"20 MB","md5":"ad918a412172a52f722cf13d753a149e"},"debarm":{"url":"https://downloads.lms-community.org/nightly/lyrionmusicserver_9.1.0~1771315634_arm.deb","version":"9.1.0","revision":"1771315634","size":"26 MB","md5":"5883248406b3cc684ea4046eb63ffa7b"},"osx":{"url":"https://downloads.lms-community.org/nightly/LyrionMusicServer-9.1.0-1771315634.dmg","version":"9.1.0","revision":"1771315634","size":"43 MB","md5":"3a79ee0d3c8d9878674f8c67d28c918d"}},"9.1.1":{"win64":{"url":"https://downloads.lms-community.org/nightly/LyrionMusicServer-9.1.1-1771531220-win64.exe","version":"9.1.1","revision":"1771531220","size":"14 MB","md5":"d970f4c576364dc065cf159bc1745125"},"macos":{"url":"https://downloads.lms-community.org/nightly/LyrionMusicServer-9.1.1-1771531220.dmg","version":"9.1.1","revision":"1771531220","size":"43 MB","md5":"2aaec8f1e20238cfed8d9de33e294dd3"},"rpm":{"url":"https://downloads.lms-community.org/nightly/lyrionmusicserver-9.1.1-0.1.1771531220.noarch.rpm","version":"9.1.1","revision":"1771531220","size":"81 MB","md5":"99787de6a75e608b62c1c572d05a1d4a"},"encore":{"url":"https://downloads.lms-community.org/nightly/lyrionmusicserver-9.1.1-1771531220-MusicalFidelity.tgz","version":"9.1.1","revision":"1771531220","size":"17 MB","md5":"925b977998312bcc4e1abefaa9b9bcb9"},"tararm":{"url":"https://downloads.lms-community.org/nightly/lyrionmusicserver-9.1.1-1771531220-arm-linux.tgz","version":"9.1.1","revision":"1771531220","size":"59 MB","md5":"086d059d7ee68de34a0dd1491b40604e"},"nocpan":{"url":"https://downloads.lms-community.org/nightly/lyrionmusicserver-9.1.1-1771531220-noCPAN.tgz","version":"9.1.1","revision":"1771531220","size":"14 MB","md5":"a138344afc099ea6298f6d09cd74ffb3"},"pcp":{"url":"https://downloads.lms-community.org/nightly/lyrionmusicserver-9.1.1-1771531220.tcz","version":"9.1.1","revision":"1771531220","size":"15 MB","md5":"e7142e1c5b2b1f4a1d0d91cb54b4661d"},"src":{"url":"https://downloads.lms-community.org/nightly/lyrionmusicserver-9.1.1-1771531220.tgz","version":"9.1.1","revision":"1771531220","size":"118 MB","md5":"8b5f9609675a87d845f5cb4491f79725"},"deb":{"url":"https://downloads.lms-community.org/nightly/lyrionmusicserver_9.1.1~1771531220_all.deb","version":"9.1.1","revision":"1771531220","size":"60 MB","md5":"1128516ad47b39ef0a83e48d3defa4b3"},"debamd64":{"url":"https://downloads.lms-community.org/nightly/lyrionmusicserver_9.1.1~1771531220_amd64.deb","version":"9.1.1","revision":"1771531220","size":"20 MB","md5":"b34cff3379ad2462b7edd59cd353b5b6"},"debarm":{"url":"https://downloads.lms-community.org/nightly/lyrionmusicserver_9.1.1~1771531220_arm.deb","version":"9.1.1","revision":"1771531220","size":"26 MB","md5":"f5556dd4f519c43be3ad40285a90da23"},"osx":{"url":"https://downloads.lms-community.org/nightly/LyrionMusicServer-9.1.1-1771531220.dmg","version":"9.1.1","revision":"1771531220","size":"43 MB","md5":"2aaec8f1e20238cfed8d9de33e294dd3"}}}