{"latest":{"win64":{"url":"https://downloads.lms-community.org/LyrionMusicServer_v9.1.0/LyrionMusicServer-9.1.0-win64.exe","version":"9.1.0","revision":"1771315634","size":"14 MB","md5":"75c285f2b8b8cde1745590beef459e5d"},"macos":{"url":"https://downloads.lms-community.org/LyrionMusicServer_v9.1.0/LyrionMusicServer-9.1.0.dmg","version":"9.1.0","revision":"1771315634","size":"43 MB","md5":"5f735a9bc5ef93b3e1fd61b3470f419b"},"rpm":{"url":"https://downloads.lms-community.org/LyrionMusicServer_v9.1.0/lyrionmusicserver-9.1.0-1.noarch.rpm","version":"9.1.0","revision":"1771315634","size":"81 MB","md5":"2cdc56b63cfbee784a51fc081bab0373"},"encore":{"url":"https://downloads.lms-community.org/LyrionMusicServer_v9.1.0/lyrionmusicserver-9.1.0-MusicalFidelity.tgz","version":"9.1.0","revision":"1771315634","size":"17 MB","md5":"499ba274349b9bcede4e5adc30bdbb43"},"tararm":{"url":"https://downloads.lms-community.org/LyrionMusicServer_v9.1.0/lyrionmusicserver-9.1.0-arm-linux.tgz","version":"9.1.0","revision":"1771315634","size":"59 MB","md5":"8a4c6fbdb6a9e7a46cb3ad5d8f75c34e"},"nocpan":{"url":"https://downloads.lms-community.org/LyrionMusicServer_v9.1.0/lyrionmusicserver-9.1.0-noCPAN.tgz","version":"9.1.0","revision":"1771315634","size":"14 MB","md5":"a1bc744bb451ff8e6cdc3f70a008f67f"},"pcp":{"url":"https://downloads.lms-community.org/LyrionMusicServer_v9.1.0/lyrionmusicserver-9.1.0.tcz","version":"9.1.0","revision":"1771315634","size":"15 MB","md5":"22344b0154752f7e3d8cd85e1c336039"},"src":{"url":"https://downloads.lms-community.org/LyrionMusicServer_v9.1.0/lyrionmusicserver-9.1.0.tgz","version":"9.1.0","revision":"1771315634","size":"118 MB","md5":"514a55d6ab736ba771542855889c7cc8"},"deb":{"url":"https://downloads.lms-community.org/LyrionMusicServer_v9.1.0/lyrionmusicserver_9.1.0_all.deb","version":"9.1.0","revision":"1771315634","size":"61 MB","md5":"744cb2339aebc1b1bd59a4521ee8a1b1"},"debamd64":{"url":"https://downloads.lms-community.org/LyrionMusicServer_v9.1.0/lyrionmusicserver_9.1.0_amd64.deb","version":"9.1.0","revision":"1771315634","size":"20 MB","md5":"eb4f9ac52218cc17af6f92722b56eb4c"},"debarm":{"url":"https://downloads.lms-community.org/LyrionMusicServer_v9.1.0/lyrionmusicserver_9.1.0_arm.deb","version":"9.1.0","revision":"1771315634","size":"26 MB","md5":"65aeaae0dd4f7fdb95617339c2846d6f"},"osx":{"url":"https://downloads.lms-community.org/LyrionMusicServer_v9.1.0/LyrionMusicServer-9.1.0.dmg","version":"9.1.0","revision":"1771315634","size":"43 MB","md5":"5f735a9bc5ef93b3e1fd61b3470f419b"}},"9.2.0":{"win64":{"url":"https://downloads.lms-community.org/nightly/LyrionMusicServer-9.2.0-1775940220-win64.exe","version":"9.2.0","revision":"1775940220","size":"14 MB","md5":"c0e25f7d18041ef642bec15f8cc2a0ae"},"macos":{"url":"https://downloads.lms-community.org/nightly/LyrionMusicServer-9.2.0-1775940220.dmg","version":"9.2.0","revision":"1775940220","size":"44 MB","md5":"0c28f44245f668846010f16589c9b609"},"rpm":{"url":"https://downloads.lms-community.org/nightly/lyrionmusicserver-9.2.0-0.1.1775940220.noarch.rpm","version":"9.2.0","revision":"1775940220","size":"82 MB","md5":"0e8f16e313a734405bed5e316a3e3f3f"},"encore":{"url":"https://downloads.lms-community.org/nightly/lyrionmusicserver-9.2.0-1775940220-MusicalFidelity.tgz","version":"9.2.0","revision":"1775940220","size":"17 MB","md5":"35920ddde5c6ec4985a77a509d4171c6"},"tararm":{"url":"https://downloads.lms-community.org/nightly/lyrionmusicserver-9.2.0-1775940220-arm-linux.tgz","version":"9.2.0","revision":"1775940220","size":"60 MB","md5":"5fe9d21f0fedabaa1027984aa88cfa7d"},"nocpan":{"url":"https://downloads.lms-community.org/nightly/lyrionmusicserver-9.2.0-1775940220-noCPAN.tgz","version":"9.2.0","revision":"1775940220","size":"15 MB","md5":"783317f0a4db2496bd800a45efd9d0df"},"pcp":{"url":"https://downloads.lms-community.org/nightly/lyrionmusicserver-9.2.0-1775940220.tcz","version":"9.2.0","revision":"1775940220","size":"16 MB","md5":"71f60839423d649e06370c9160d91214"},"src":{"url":"https://downloads.lms-community.org/nightly/lyrionmusicserver-9.2.0-1775940220.tgz","version":"9.2.0","revision":"1775940220","size":"118 MB","md5":"a283aca67348dbd4f97c650bc2e0eaf0"},"deb":{"url":"https://downloads.lms-community.org/nightly/lyrionmusicserver_9.2.0~1775940220_all.deb","version":"9.2.0","revision":"1775940220","size":"61 MB","md5":"41a4f4662cef5f6db557fb15c6b4088f"},"debamd64":{"url":"https://downloads.lms-community.org/nightly/lyrionmusicserver_9.2.0~1775940220_amd64.deb","version":"9.2.0","revision":"1775940220","size":"21 MB","md5":"8a0f3754fe854803bed8dd0be71d0cdb"},"debarm":{"url":"https://downloads.lms-community.org/nightly/lyrionmusicserver_9.2.0~1775940220_arm.deb","version":"9.2.0","revision":"1775940220","size":"26 MB","md5":"bb609394befbea1dc3aca4092246b47e"},"osx":{"url":"https://downloads.lms-community.org/nightly/LyrionMusicServer-9.2.0-1775940220.dmg","version":"9.2.0","revision":"1775940220","size":"44 MB","md5":"0c28f44245f668846010f16589c9b609"}},"9.1.1":{"win64":{"url":"https://downloads.lms-community.org/nightly/LyrionMusicServer-9.1.1-1775393014-win64.exe","version":"9.1.1","revision":"1775393014","size":"14 MB","md5":"7703a5b9649b5d14c134f749629afcbd"},"macos":{"url":"https://downloads.lms-community.org/nightly/LyrionMusicServer-9.1.1-1775393014.dmg","version":"9.1.1","revision":"1775393014","size":"43 MB","md5":"ae4c8ceccb4aea2ed1e1c805d8975fe9"},"rpm":{"url":"https://downloads.lms-community.org/nightly/lyrionmusicserver-9.1.1-0.1.1775393014.noarch.rpm","version":"9.1.1","revision":"1775393014","size":"81 MB","md5":"e3489079e3b48fed58b1d670ae958488"},"encore":{"url":"https://downloads.lms-community.org/nightly/lyrionmusicserver-9.1.1-1775393014-MusicalFidelity.tgz","version":"9.1.1","revision":"1775393014","size":"17 MB","md5":"1ec25b7ffd2bdfc33f661dbfdb0d1430"},"tararm":{"url":"https://downloads.lms-community.org/nightly/lyrionmusicserver-9.1.1-1775393014-arm-linux.tgz","version":"9.1.1","revision":"1775393014","size":"59 MB","md5":"e9463f5dc5c177a500871b54a82cd890"},"nocpan":{"url":"https://downloads.lms-community.org/nightly/lyrionmusicserver-9.1.1-1775393014-noCPAN.tgz","version":"9.1.1","revision":"1775393014","size":"14 MB","md5":"febd7eb16cce1d2ad1506d0943a68cb8"},"pcp":{"url":"https://downloads.lms-community.org/nightly/lyrionmusicserver-9.1.1-1775393014.tcz","version":"9.1.1","revision":"1775393014","size":"15 MB","md5":"49f5946f3c8d30bd2cef618209acadbd"},"src":{"url":"https://downloads.lms-community.org/nightly/lyrionmusicserver-9.1.1-1775393014.tgz","version":"9.1.1","revision":"1775393014","size":"118 MB","md5":"40a955179c0799e2972ac8e697301cab"},"deb":{"url":"https://downloads.lms-community.org/nightly/lyrionmusicserver_9.1.1~1775393014_all.deb","version":"9.1.1","revision":"1775393014","size":"61 MB","md5":"1492241bc478a845a813f881e9fdf378"},"debamd64":{"url":"https://downloads.lms-community.org/nightly/lyrionmusicserver_9.1.1~1775393014_amd64.deb","version":"9.1.1","revision":"1775393014","size":"20 MB","md5":"a6fe9e9da023f0ad0a530c173e1df9c9"},"debarm":{"url":"https://downloads.lms-community.org/nightly/lyrionmusicserver_9.1.1~1775393014_arm.deb","version":"9.1.1","revision":"1775393014","size":"26 MB","md5":"87077d5600f4ee1a1dc03f6b30de6e3a"},"osx":{"url":"https://downloads.lms-community.org/nightly/LyrionMusicServer-9.1.1-1775393014.dmg","version":"9.1.1","revision":"1775393014","size":"43 MB","md5":"ae4c8ceccb4aea2ed1e1c805d8975fe9"}}}