<servers><win64 url="https://downloads.lms-community.org/nightly/LyrionMusicServer-9.0.3-1743682054-win64.exe" version="9.0.3" revision="1743682054" size="17 MB" md5="2ebbeba36e306399f650990e008b4e6e"/><macos url="https://downloads.lms-community.org/nightly/LyrionMusicServer-9.0.3-1743682054.dmg" version="9.0.3" revision="1743682054" size="45 MB" md5="14add4a3f5bf1a7164504c3c1e2a18f4"/><rpm url="https://downloads.lms-community.org/nightly/lyrionmusicserver-9.0.3-0.1.1743682054.noarch.rpm" version="9.0.3" revision="1743682054" size="89 MB" md5="b6553873efacade2672d6312b74ca680"/><pcp url="https://downloads.lms-community.org/nightly/lyrionmusicserver-9.0.3-1742711205.tcz" version="9.0.3" revision="1742711205" size="17 MB" md5="3d0276d4b4fdb2170a310c99a4ba2a7e"/><encore url="https://downloads.lms-community.org/nightly/lyrionmusicserver-9.0.3-1743682054-MusicalFidelity.tgz" version="9.0.3" revision="1743682054" size="19 MB" md5="420436497263ec33c30fede332ade126"/><tararm url="https://downloads.lms-community.org/nightly/lyrionmusicserver-9.0.3-1743682054-arm-linux.tgz" version="9.0.3" revision="1743682054" size="56 MB" md5="6ab7e29efe47f3075920aa2c3f976b57"/><nocpan url="https://downloads.lms-community.org/nightly/lyrionmusicserver-9.0.3-1743682054-noCPAN.tgz" version="9.0.3" revision="1743682054" size="17 MB" md5="a80778be7050dec55aead5a70fcab10e"/><src url="https://downloads.lms-community.org/nightly/lyrionmusicserver-9.0.3-1743682054.tgz" version="9.0.3" revision="1743682054" size="120 MB" md5="f26c8ff6ff4c6164b7ecdfd257338fcd"/><deb url="https://downloads.lms-community.org/nightly/lyrionmusicserver_9.0.3~1743682054_all.deb" version="9.0.3" revision="1743682054" size="58 MB" md5="e5f3dd750948c8f5d0ef1f1fce2edf0e"/><debamd64 url="https://downloads.lms-community.org/nightly/lyrionmusicserver_9.0.3~1743682054_amd64.deb" version="9.0.3" revision="1743682054" size="25 MB" md5="75914b246cd5e1fa222dc4806aff666a"/><debarm url="https://downloads.lms-community.org/nightly/lyrionmusicserver_9.0.3~1743682054_arm.deb" version="9.0.3" revision="1743682054" size="32 MB" md5="af7b88bdc6bf3fc15c8b94a1ad5c18a5"/><debi386 url="https://downloads.lms-community.org/nightly/lyrionmusicserver_9.0.3~1743682054_i386.deb" version="9.0.3" revision="1743682054" size="17 MB" md5="d7d4d1cb242f1dbf7e89da767dcd88e2"/><osx url="https://downloads.lms-community.org/nightly/LyrionMusicServer-9.0.3-1743682054.dmg" version="9.0.3" revision="1743682054" size="45 MB" md5="14add4a3f5bf1a7164504c3c1e2a18f4"/></servers>