<servers><win64 url="https://downloads.lms-community.org/nightly/LyrionMusicServer-9.1.1-1779514884-win64.exe" version="9.1.1" revision="1779514884" size="14 MB" md5="0cd2418da55c709d335491496c677f8e"/><macos url="https://downloads.lms-community.org/nightly/LyrionMusicServer-9.1.1-1779514884.dmg" version="9.1.1" revision="1779514884" size="43 MB" md5="1268300307d5eb88ceb7f1f05072f0ca"/><rpm url="https://downloads.lms-community.org/nightly/lyrionmusicserver-9.1.1-0.1.1779514884.noarch.rpm" version="9.1.1" revision="1779514884" size="81 MB" md5="b7de2d7fd87140d5cd9f127d04e62ea7"/><encore url="https://downloads.lms-community.org/nightly/lyrionmusicserver-9.1.1-1779514884-MusicalFidelity.tgz" version="9.1.1" revision="1779514884" size="17 MB" md5="65b5ec54078539035db693f1d9bf3592"/><tararm url="https://downloads.lms-community.org/nightly/lyrionmusicserver-9.1.1-1779514884-arm-linux.tgz" version="9.1.1" revision="1779514884" size="59 MB" md5="18258ef7ceb4d7427cbdafdbe053d165"/><nocpan url="https://downloads.lms-community.org/nightly/lyrionmusicserver-9.1.1-1779514884-noCPAN.tgz" version="9.1.1" revision="1779514884" size="14 MB" md5="07f2739c878a1f3414f72a06b0036d0c"/><pcp url="https://downloads.lms-community.org/nightly/lyrionmusicserver-9.1.1-1779514884.tcz" version="9.1.1" revision="1779514884" size="15 MB" md5="736a26d48a33a2b032f23fde4c13acd7"/><src url="https://downloads.lms-community.org/nightly/lyrionmusicserver-9.1.1-1779514884.tgz" version="9.1.1" revision="1779514884" size="118 MB" md5="347e60f3634c4c7fbb8514b1ea42466c"/><deb url="https://downloads.lms-community.org/nightly/lyrionmusicserver_9.1.1~1779514884_all.deb" version="9.1.1" revision="1779514884" size="60 MB" md5="d46598fee2c10e22cd0712c82c542682"/><debamd64 url="https://downloads.lms-community.org/nightly/lyrionmusicserver_9.1.1~1779514884_amd64.deb" version="9.1.1" revision="1779514884" size="20 MB" md5="983167b1fef765f832c8402229f31fbb"/><debarm url="https://downloads.lms-community.org/nightly/lyrionmusicserver_9.1.1~1779514884_arm.deb" version="9.1.1" revision="1779514884" size="26 MB" md5="2b082bdb3c9625cdb66177639314dd9f"/><osx url="https://downloads.lms-community.org/nightly/LyrionMusicServer-9.1.1-1779514884.dmg" version="9.1.1" revision="1779514884" size="43 MB" md5="1268300307d5eb88ceb7f1f05072f0ca"/></servers>